dgd/__init__.py
dgd/_download.py
dgd/config.py
dgd/inference.py
dgd/py.typed
dgd/video.py
dgd-0.0.0.dist-info/LICENSE
dgd-0.0.0.dist-info/METADATA
dgd-0.0.0.dist-info/WHEEL
dgd-0.0.0.dist-info/top_level.txt
dgd-0.0.0.dist-info/RECORD
